django_setup_env-0.6.dist-info/DESCRIPTION.rst
django_setup_env-0.6.dist-info/METADATA
django_setup_env-0.6.dist-info/metadata.json
django_setup_env-0.6.dist-info/WHEEL
django_setup_env-0.6.dist-info/RECORD
django_setup_env-0.6.dist-info/top_level.txt
django_setup_env/__init__.py
