Metadata-Version: 2.0
Name: django-setup-env
Version: 0.6
Summary: Tool to setup Django in standalone scripts
Home-page: UNKNOWN
Author: Alasdair Nicol
Author-email: alasdair.nicol@spatialbuzz.com
License: MIT
Platform: UNKNOWN
